HelloProject/Hello.py
HelloProject/_init_.py
busisfirstpackage-1.0.0.dist-info/METADATA
busisfirstpackage-1.0.0.dist-info/WHEEL
busisfirstpackage-1.0.0.dist-info/top_level.txt
busisfirstpackage-1.0.0.dist-info/RECORD
