Metadata-Version: 2.1
Name: busisfirstpackage
Version: 1.0.0
Summary: This is Busi's fiest package.
Author: Busi Phathela
Author-email: muvhusophathela@gmail.com
